movie_info_downloader/__init__.py
movie_info_downloader-0.0.1.dist-info/DESCRIPTION.rst
movie_info_downloader-0.0.1.dist-info/METADATA
movie_info_downloader-0.0.1.dist-info/RECORD
movie_info_downloader-0.0.1.dist-info/WHEEL
movie_info_downloader-0.0.1.dist-info/metadata.json
movie_info_downloader-0.0.1.dist-info/top_level.txt
