Metadata-Version: 2.0
Name: movie-info-downloader
Version: 0.0.1
Summary: A simple package to get info from imdb about newest torrent movies using rss file
Home-page: http://packages.python.org/movie_info_downloader
Author: Kamil Rogalski
Author-email: drootnar@gmail.com
License: BSD
Keywords: torrent rss imdb
Platform: UNKNOWN
Classifier: Development Status :: 3 - Alpha
Classifier: Topic :: Utilities
Classifier: License :: OSI Approved :: BSD License
